translatetool/__init__.py
translatetool/translater.py
translatetool-1.0.2.dist-info/METADATA
translatetool-1.0.2.dist-info/WHEEL
translatetool-1.0.2.dist-info/top_level.txt
translatetool-1.0.2.dist-info/RECORD
