Metadata-Version: 2.1
Name: translatetool
Version: 1.0.2
Summary: A Papago Translate module.
Home-page: https://github.com/jaewoolee82/translatetool
Author: Jaewoo Lee
Author-email: jaewoolee82@kakao.com
License: MIT
Platform: UNKNOWN
Requires-Python: >=3
